activeSVC/__init__.py
activeSVC-4.0.1.dist-info/LICENSE
activeSVC-4.0.1.dist-info/METADATA
activeSVC-4.0.1.dist-info/WHEEL
activeSVC-4.0.1.dist-info/top_level.txt
activeSVC-4.0.1.dist-info/RECORD
