Metadata-Version: 2.1
Name: activeSVC
Version: 4.0.1
Summary: Active feature selection method with support vector classifier.
Home-page: https://github.com/xqchen/activeSVC
Author: Xiaoqiao Chen
Author-email: xqchen@caltech.edu
License: UNKNOWN
Platform: UNKNOWN
Classifier: Programming Language :: Python :: 2.7
Classifier: Programming Language :: Python :: 3
Classifier: License :: OSI Approved :: GNU General Public License v3 (GPLv3)
Classifier: Operating System :: OS Independent
Requires-Python: >=3.1
License-File: LICENSE
